hd_tma/__init__.py
hd_tma/hough.py
hd_tma/tmf.py
Hough_TMF-0.2.5.dist-info/LICENCE
Hough_TMF-0.2.5.dist-info/METADATA
Hough_TMF-0.2.5.dist-info/WHEEL
Hough_TMF-0.2.5.dist-info/top_level.txt
Hough_TMF-0.2.5.dist-info/RECORD
