Metadata-Version: 2.1
Name: Hough-TMF
Version: 0.2.5
Summary: A package for template matching using Torch
Home-page: 
Author: Hao Lv
Author-email: lh21@apm.ac.cn
License: MIT
Classifier: Programming Language :: Python :: 3
Classifier: License :: OSI Approved :: MIT License
Classifier: Operating System :: OS Independent
Requires-Python: >=3.9
License-File: LICENCE
